create_sequel_app.py
create-sequel-app/__init__.py
create-sequel-app/template_project/.DS_Store
create-sequel-app/template_project/.env
create-sequel-app/template_project/License.md
create-sequel-app/template_project/Pipfile
create-sequel-app/template_project/Pipfile.lock
create-sequel-app/template_project/README.md
create-sequel-app/template_project/app.py
create-sequel-app/template_project/app_router.py
create-sequel-app/template_project/example_env
create-sequel-app/template_project/api/user/route.py
create-sequel-app/template_project/components/example_use_form.py
create-sequel-app/template_project/direct_pages/example.html
create-sequel-app/template_project/routes/not_found.py
create-sequel-app/template_project/routes/page.py
create-sequel-app/template_project/routes/__pycache__/page.cpython-310.pyc
create-sequel-app/template_project/routes/user/__init__.py
create-sequel-app/template_project/routes/user/page.py
create-sequel-app/template_project/routes/user/[id]/__init__.py
create-sequel-app/template_project/routes/user/[id]/page.py
create-sequel-app/template_project/routes/user/[id]/__pycache__/page.cpython-310.pyc
create-sequel-app/template_project/routes/user/__pycache__/[id].cpython-310.pyc
create-sequel-app/template_project/routes/user/__pycache__/_[id].cpython-310.pyc
create-sequel-app/template_project/routes/user/__pycache__/page.cpython-310.pyc
create_sequel_app-0.3.9.dist-info/METADATA
create_sequel_app-0.3.9.dist-info/WHEEL
create_sequel_app-0.3.9.dist-info/entry_points.txt
create_sequel_app-0.3.9.dist-info/top_level.txt
create_sequel_app-0.3.9.dist-info/RECORD
