Metadata-Version: 2.1
Name: create-sequel-app
Version: 0.3.9
Summary: Create a new Sequel project
Author: Kyle Lee
Author-email: kyle@kylelee.dev
Classifier: Development Status :: 3 - Alpha
Classifier: Intended Audience :: Developers
Classifier: License :: OSI Approved :: MIT License
Classifier: Programming Language :: Python :: 3
Requires-Python: >=3.7
Requires-Dist: Click
